regcore/__init__.py
regcore/fields.py
regcore/index.py
regcore/layer.py
regcore/models.py
regcore/responses.py
regcore/search_indexes.py
regcore/urls.py
regcore/urls_utils.py
regcore/db/__init__.py
regcore/db/django_models.py
regcore/db/es.py
regcore/db/interface.py
regcore/db/storage.py
regcore/management/__init__.py
regcore/management/commands/__init__.py
regcore/management/commands/import_docs.py
regcore/migrations/0001_initial.py
regcore/migrations/0002_mptt_add_fields.py
regcore/migrations/0002_preamble.py
regcore/migrations/0003_mptt_copy_children.py
regcore/migrations/0004_mptt_delete_fields.py
regcore/migrations/0005_merge.py
regcore/migrations/0006_auto_20160314_1126.py
regcore/migrations/0007_auto_20160314_1135.py
regcore/migrations/0008_auto_20160314_1144.py
regcore/migrations/0009_auto_20160322_1646.py
regcore/migrations/0010_auto_20160322_1704.py
regcore/migrations/0011_create_document.py
regcore/migrations/0012_migrate_documents.py
regcore/migrations/0013_remove_models.py
regcore/migrations/0014_auto_20160504_0101.py
regcore/migrations/__init__.py
regcore/settings/__init__.py
regcore/settings/base.py
regcore/settings/elastic.py
regcore/settings/pgsql.py
regcore/templates/search/indexes/regcore/document_text.txt
regcore/tests/__init__.py
regcore/tests/db_django_models_tests.py
regcore/tests/db_es_tests.py
regcore/tests/fields_tests.py
regcore/tests/index_tests.py
regcore/tests/layer_tests.py
regcore/tests/recipes.py
regcore/tests/responses_tests.py
regcore/tests/management/__init__.py
regcore/tests/management/commands/__init__.py
regcore/tests/management/commands/import_docs_tests.py
regcore-4.2.0.dist-info/DESCRIPTION.rst
regcore-4.2.0.dist-info/METADATA
regcore-4.2.0.dist-info/RECORD
regcore-4.2.0.dist-info/WHEEL
regcore-4.2.0.dist-info/metadata.json
regcore-4.2.0.dist-info/top_level.txt
regcore_pgsql/__init__.py
regcore_pgsql/models.py
regcore_pgsql/views.py
regcore_pgsql/management/__init__.py
regcore_pgsql/management/commands/__init__.py
regcore_pgsql/management/commands/rebuild_pgsql_index.py
regcore_pgsql/migrations/0001_initial.py
regcore_pgsql/migrations/0002_documentindex_doc_root.py
